{"h1":"Android handwriting recognition  libraries","title":"List of all Android handwriting recognition  libraries for use in your project","meta":"See collection of all Android handwriting recognition  libraries, filter by license, modified date, languages, and select best for your usecase.","repoList":[{"name":"Ocr-android","language":"Java","description":"\u2b55 Text recognition, Leptonica-based deep learning technology, the text on the picture, intelligent recognition as editable text. Support printing and handwriting recognition, including ID cards, business cards and other card types, but also support notes, waybills and other customized scene identification, can effectively replace the manual entry of information scenes. Available in both Chinese and English language libraries, recognition accuracy up to 94%. No networking required.","fullName":"shenhuanet\/Ocr-android","updatedAt":"2020-08-07T09:21:44Z","gitUrl":"https:\/\/github.com\/shenhuanet\/Ocr-android","license":"GNU General Public License v2.0","forks":14,"stargazersCount":19}]}