{"h1":"Android database  libraries","title":"List of all Android database  libraries for use in your project","meta":"See collection of all Android database  libraries, filter by license, modified date, languages, and select best for your usecase.","repoList":[{"name":"Android-Debug-Database","language":"Java","description":"A library for debugging android databases and shared preferences - Make Debugging Great Again","fullName":"amitshekhariitbhu\/Android-Debug-Database","updatedAt":"2020-11-20T15:15:17Z","gitUrl":"https:\/\/github.com\/amitshekhariitbhu\/Android-Debug-Database","license":"Apache License 2.0","forks":796,"stargazersCount":7593},{"name":"AndroidDatabaseLibraryComparison","language":"Java","description":null,"fullName":"Rightpoint\/AndroidDatabaseLibraryComparison","updatedAt":"2020-10-20T22:21:11Z","gitUrl":"https:\/\/github.com\/Rightpoint\/AndroidDatabaseLibraryComparison","license":"MIT License","forks":43,"stargazersCount":148},{"name":"LitePal","language":"Java","description":"An Android library that makes developers use SQLite database extremely easy.","fullName":"guolindev\/LitePal","updatedAt":"2020-11-20T07:35:43Z","gitUrl":"https:\/\/github.com\/guolindev\/LitePal","license":"Apache License 2.0","forks":1532,"stargazersCount":7389},{"name":"android_dbinspector","language":"Kotlin","description":"Android library for viewing and sharing in app databases.","fullName":"infinum\/android_dbinspector","updatedAt":"2020-11-18T14:27:05Z","gitUrl":"https:\/\/github.com\/infinum\/android_dbinspector","license":"Apache License 2.0","forks":90,"stargazersCount":870},{"name":"DBFlow","language":"Kotlin","description":"A blazing fast, powerful, and very simple ORM android database library that writes database code for you.","fullName":"agrosner\/DBFlow","updatedAt":"2020-11-18T05:36:17Z","gitUrl":"https:\/\/github.com\/agrosner\/DBFlow","license":"MIT License","forks":607,"stargazersCount":4786},{"name":"squidb","language":"Java","description":"SquiDB is a SQLite database library for Android and iOS","fullName":"yahoo\/squidb","updatedAt":"2020-11-16T10:56:00Z","gitUrl":"https:\/\/github.com\/yahoo\/squidb","license":"Apache License 2.0","forks":132,"stargazersCount":1322},{"name":"hyperlog-android","language":"Java","description":"Utility logger library for storing logs into database and push them to remote server for debugging","fullName":"hypertrack\/hyperlog-android","updatedAt":"2020-11-11T23:08:15Z","gitUrl":"https:\/\/github.com\/hypertrack\/hyperlog-android","license":null,"forks":96,"stargazersCount":644},{"name":"RoomDatabase","language":"Java","description":"Android Architecture Component - Room Persistency Library example","fullName":"ravi8x\/RoomDatabase","updatedAt":"2020-06-20T19:32:28Z","gitUrl":"https:\/\/github.com\/ravi8x\/RoomDatabase","license":null,"forks":16,"stargazersCount":35},{"name":"room-persistence-sample","language":"Java","description":"Implementation of Room Persistence Library","fullName":"ajaysaini-sgvu\/room-persistence-sample","updatedAt":"2020-11-18T21:15:07Z","gitUrl":"https:\/\/github.com\/ajaysaini-sgvu\/room-persistence-sample","license":null,"forks":44,"stargazersCount":88},{"name":"sprinkles","language":"Java","description":"Sprinkles is a boiler-plate-reduction-library for dealing with databases in android applications","fullName":"emilsjolander\/sprinkles","updatedAt":"2020-10-28T08:46:53Z","gitUrl":"https:\/\/github.com\/emilsjolander\/sprinkles","license":"Apache License 2.0","forks":84,"stargazersCount":789},{"name":"Android-Debug-Database","language":"Java","description":"A library for debugging android databases and shared preferences - Make Debugging Great Again","fullName":"amitshekhariitbhu\/Android-Debug-Database","updatedAt":"2020-11-20T15:15:17Z","gitUrl":"https:\/\/github.com\/amitshekhariitbhu\/Android-Debug-Database","license":"Apache License 2.0","forks":796,"stargazersCount":7593},{"name":"AndroidDatabaseLibraryComparison","language":"Java","description":null,"fullName":"Rightpoint\/AndroidDatabaseLibraryComparison","updatedAt":"2020-10-20T22:21:11Z","gitUrl":"https:\/\/github.com\/Rightpoint\/AndroidDatabaseLibraryComparison","license":"MIT License","forks":43,"stargazersCount":148},{"name":"LitePal","language":"Java","description":"An Android library that makes developers use SQLite database extremely easy.","fullName":"guolindev\/LitePal","updatedAt":"2020-11-20T07:35:43Z","gitUrl":"https:\/\/github.com\/guolindev\/LitePal","license":"Apache License 2.0","forks":1532,"stargazersCount":7389},{"name":"android_dbinspector","language":"Kotlin","description":"Android library for viewing and sharing in app databases.","fullName":"infinum\/android_dbinspector","updatedAt":"2020-11-18T14:27:05Z","gitUrl":"https:\/\/github.com\/infinum\/android_dbinspector","license":"Apache License 2.0","forks":90,"stargazersCount":870},{"name":"DBFlow","language":"Kotlin","description":"A blazing fast, powerful, and very simple ORM android database library that writes database code for you.","fullName":"agrosner\/DBFlow","updatedAt":"2020-11-18T05:36:17Z","gitUrl":"https:\/\/github.com\/agrosner\/DBFlow","license":"MIT License","forks":607,"stargazersCount":4786},{"name":"squidb","language":"Java","description":"SquiDB is a SQLite database library for Android and iOS","fullName":"yahoo\/squidb","updatedAt":"2020-11-16T10:56:00Z","gitUrl":"https:\/\/github.com\/yahoo\/squidb","license":"Apache License 2.0","forks":132,"stargazersCount":1322},{"name":"hyperlog-android","language":"Java","description":"Utility logger library for storing logs into database and push them to remote server for debugging","fullName":"hypertrack\/hyperlog-android","updatedAt":"2020-11-11T23:08:15Z","gitUrl":"https:\/\/github.com\/hypertrack\/hyperlog-android","license":null,"forks":96,"stargazersCount":644},{"name":"RoomDatabase","language":"Java","description":"Android Architecture Component - Room Persistency Library example","fullName":"ravi8x\/RoomDatabase","updatedAt":"2020-06-20T19:32:28Z","gitUrl":"https:\/\/github.com\/ravi8x\/RoomDatabase","license":null,"forks":16,"stargazersCount":35},{"name":"room-persistence-sample","language":"Java","description":"Implementation of Room Persistence Library","fullName":"ajaysaini-sgvu\/room-persistence-sample","updatedAt":"2020-11-18T21:15:07Z","gitUrl":"https:\/\/github.com\/ajaysaini-sgvu\/room-persistence-sample","license":null,"forks":44,"stargazersCount":88},{"name":"sprinkles","language":"Java","description":"Sprinkles is a boiler-plate-reduction-library for dealing with databases in android applications","fullName":"emilsjolander\/sprinkles","updatedAt":"2020-10-28T08:46:53Z","gitUrl":"https:\/\/github.com\/emilsjolander\/sprinkles","license":"Apache License 2.0","forks":84,"stargazersCount":789},{"name":"Android-Debug-Database","language":"Java","description":"A library for debugging android databases and shared preferences - Make Debugging Great Again","fullName":"amitshekhariitbhu\/Android-Debug-Database","updatedAt":"2020-11-20T15:15:17Z","gitUrl":"https:\/\/github.com\/amitshekhariitbhu\/Android-Debug-Database","license":"Apache License 2.0","forks":796,"stargazersCount":7593},{"name":"AndroidDatabaseLibraryComparison","language":"Java","description":null,"fullName":"Rightpoint\/AndroidDatabaseLibraryComparison","updatedAt":"2020-10-20T22:21:11Z","gitUrl":"https:\/\/github.com\/Rightpoint\/AndroidDatabaseLibraryComparison","license":"MIT License","forks":43,"stargazersCount":148},{"name":"LitePal","language":"Java","description":"An Android library that makes developers use SQLite database extremely easy.","fullName":"guolindev\/LitePal","updatedAt":"2020-11-20T07:35:43Z","gitUrl":"https:\/\/github.com\/guolindev\/LitePal","license":"Apache License 2.0","forks":1532,"stargazersCount":7389},{"name":"android_dbinspector","language":"Kotlin","description":"Android library for viewing and sharing in app databases.","fullName":"infinum\/android_dbinspector","updatedAt":"2020-11-18T14:27:05Z","gitUrl":"https:\/\/github.com\/infinum\/android_dbinspector","license":"Apache License 2.0","forks":90,"stargazersCount":870},{"name":"DBFlow","language":"Kotlin","description":"A blazing fast, powerful, and very simple ORM android database library that writes database code for you.","fullName":"agrosner\/DBFlow","updatedAt":"2020-11-18T05:36:17Z","gitUrl":"https:\/\/github.com\/agrosner\/DBFlow","license":"MIT License","forks":607,"stargazersCount":4786},{"name":"squidb","language":"Java","description":"SquiDB is a SQLite database library for Android and iOS","fullName":"yahoo\/squidb","updatedAt":"2020-11-16T10:56:00Z","gitUrl":"https:\/\/github.com\/yahoo\/squidb","license":"Apache License 2.0","forks":132,"stargazersCount":1322},{"name":"hyperlog-android","language":"Java","description":"Utility logger library for storing logs into database and push them to remote server for debugging","fullName":"hypertrack\/hyperlog-android","updatedAt":"2020-11-11T23:08:15Z","gitUrl":"https:\/\/github.com\/hypertrack\/hyperlog-android","license":null,"forks":96,"stargazersCount":644},{"name":"RoomDatabase","language":"Java","description":"Android Architecture Component - Room Persistency Library example","fullName":"ravi8x\/RoomDatabase","updatedAt":"2020-06-20T19:32:28Z","gitUrl":"https:\/\/github.com\/ravi8x\/RoomDatabase","license":null,"forks":16,"stargazersCount":35},{"name":"room-persistence-sample","language":"Java","description":"Implementation of Room Persistence Library","fullName":"ajaysaini-sgvu\/room-persistence-sample","updatedAt":"2020-11-18T21:15:07Z","gitUrl":"https:\/\/github.com\/ajaysaini-sgvu\/room-persistence-sample","license":null,"forks":44,"stargazersCount":88},{"name":"sprinkles","language":"Java","description":"Sprinkles is a boiler-plate-reduction-library for dealing with databases in android applications","fullName":"emilsjolander\/sprinkles","updatedAt":"2020-10-28T08:46:53Z","gitUrl":"https:\/\/github.com\/emilsjolander\/sprinkles","license":"Apache License 2.0","forks":84,"stargazersCount":789},{"name":"Android-Debug-Database","language":"Java","description":"A library for debugging android databases and shared preferences - Make Debugging Great Again","fullName":"amitshekhariitbhu\/Android-Debug-Database","updatedAt":"2020-11-20T15:15:17Z","gitUrl":"https:\/\/github.com\/amitshekhariitbhu\/Android-Debug-Database","license":"Apache License 2.0","forks":796,"stargazersCount":7593},{"name":"AndroidDatabaseLibraryComparison","language":"Java","description":null,"fullName":"Rightpoint\/AndroidDatabaseLibraryComparison","updatedAt":"2020-10-20T22:21:11Z","gitUrl":"https:\/\/github.com\/Rightpoint\/AndroidDatabaseLibraryComparison","license":"MIT License","forks":43,"stargazersCount":148},{"name":"LitePal","language":"Java","description":"An Android library that makes developers use SQLite database extremely easy.","fullName":"guolindev\/LitePal","updatedAt":"2020-11-20T07:35:43Z","gitUrl":"https:\/\/github.com\/guolindev\/LitePal","license":"Apache License 2.0","forks":1532,"stargazersCount":7389},{"name":"android_dbinspector","language":"Kotlin","description":"Android library for viewing and sharing in app databases.","fullName":"infinum\/android_dbinspector","updatedAt":"2020-11-18T14:27:05Z","gitUrl":"https:\/\/github.com\/infinum\/android_dbinspector","license":"Apache License 2.0","forks":90,"stargazersCount":870},{"name":"DBFlow","language":"Kotlin","description":"A blazing fast, powerful, and very simple ORM android database library that writes database code for you.","fullName":"agrosner\/DBFlow","updatedAt":"2020-11-18T05:36:17Z","gitUrl":"https:\/\/github.com\/agrosner\/DBFlow","license":"MIT License","forks":607,"stargazersCount":4786},{"name":"squidb","language":"Java","description":"SquiDB is a SQLite database library for Android and iOS","fullName":"yahoo\/squidb","updatedAt":"2020-11-16T10:56:00Z","gitUrl":"https:\/\/github.com\/yahoo\/squidb","license":"Apache License 2.0","forks":132,"stargazersCount":1322},{"name":"hyperlog-android","language":"Java","description":"Utility logger library for storing logs into database and push them to remote server for debugging","fullName":"hypertrack\/hyperlog-android","updatedAt":"2020-11-11T23:08:15Z","gitUrl":"https:\/\/github.com\/hypertrack\/hyperlog-android","license":null,"forks":96,"stargazersCount":644},{"name":"RoomDatabase","language":"Java","description":"Android Architecture Component - Room Persistency Library example","fullName":"ravi8x\/RoomDatabase","updatedAt":"2020-06-20T19:32:28Z","gitUrl":"https:\/\/github.com\/ravi8x\/RoomDatabase","license":null,"forks":16,"stargazersCount":35},{"name":"room-persistence-sample","language":"Java","description":"Implementation of Room Persistence Library","fullName":"ajaysaini-sgvu\/room-persistence-sample","updatedAt":"2020-11-18T21:15:07Z","gitUrl":"https:\/\/github.com\/ajaysaini-sgvu\/room-persistence-sample","license":null,"forks":44,"stargazersCount":88},{"name":"sprinkles","language":"Java","description":"Sprinkles is a boiler-plate-reduction-library for dealing with databases in android applications","fullName":"emilsjolander\/sprinkles","updatedAt":"2020-10-28T08:46:53Z","gitUrl":"https:\/\/github.com\/emilsjolander\/sprinkles","license":"Apache License 2.0","forks":84,"stargazersCount":789},{"name":"Android-Debug-Database","language":"Java","description":"A library for debugging android databases and shared preferences - Make Debugging Great Again","fullName":"amitshekhariitbhu\/Android-Debug-Database","updatedAt":"2020-11-20T15:15:17Z","gitUrl":"https:\/\/github.com\/amitshekhariitbhu\/Android-Debug-Database","license":"Apache License 2.0","forks":796,"stargazersCount":7593},{"name":"AndroidDatabaseLibraryComparison","language":"Java","description":null,"fullName":"Rightpoint\/AndroidDatabaseLibraryComparison","updatedAt":"2020-10-20T22:21:11Z","gitUrl":"https:\/\/github.com\/Rightpoint\/AndroidDatabaseLibraryComparison","license":"MIT License","forks":43,"stargazersCount":148},{"name":"LitePal","language":"Java","description":"An Android library that makes developers use SQLite database extremely easy.","fullName":"guolindev\/LitePal","updatedAt":"2020-11-20T07:35:43Z","gitUrl":"https:\/\/github.com\/guolindev\/LitePal","license":"Apache License 2.0","forks":1532,"stargazersCount":7389},{"name":"android_dbinspector","language":"Kotlin","description":"Android library for viewing and sharing in app databases.","fullName":"infinum\/android_dbinspector","updatedAt":"2020-11-18T14:27:05Z","gitUrl":"https:\/\/github.com\/infinum\/android_dbinspector","license":"Apache License 2.0","forks":90,"stargazersCount":870},{"name":"DBFlow","language":"Kotlin","description":"A blazing fast, powerful, and very simple ORM android database library that writes database code for you.","fullName":"agrosner\/DBFlow","updatedAt":"2020-11-18T05:36:17Z","gitUrl":"https:\/\/github.com\/agrosner\/DBFlow","license":"MIT License","forks":607,"stargazersCount":4786},{"name":"squidb","language":"Java","description":"SquiDB is a SQLite database library for Android and iOS","fullName":"yahoo\/squidb","updatedAt":"2020-11-16T10:56:00Z","gitUrl":"https:\/\/github.com\/yahoo\/squidb","license":"Apache License 2.0","forks":132,"stargazersCount":1322},{"name":"hyperlog-android","language":"Java","description":"Utility logger library for storing logs into database and push them to remote server for debugging","fullName":"hypertrack\/hyperlog-android","updatedAt":"2020-11-11T23:08:15Z","gitUrl":"https:\/\/github.com\/hypertrack\/hyperlog-android","license":null,"forks":96,"stargazersCount":644},{"name":"RoomDatabase","language":"Java","description":"Android Architecture Component - Room Persistency Library example","fullName":"ravi8x\/RoomDatabase","updatedAt":"2020-06-20T19:32:28Z","gitUrl":"https:\/\/github.com\/ravi8x\/RoomDatabase","license":null,"forks":16,"stargazersCount":35},{"name":"room-persistence-sample","language":"Java","description":"Implementation of Room Persistence Library","fullName":"ajaysaini-sgvu\/room-persistence-sample","updatedAt":"2020-11-18T21:15:07Z","gitUrl":"https:\/\/github.com\/ajaysaini-sgvu\/room-persistence-sample","license":null,"forks":44,"stargazersCount":88},{"name":"sprinkles","language":"Java","description":"Sprinkles is a boiler-plate-reduction-library for dealing with databases in android applications","fullName":"emilsjolander\/sprinkles","updatedAt":"2020-10-28T08:46:53Z","gitUrl":"https:\/\/github.com\/emilsjolander\/sprinkles","license":"Apache License 2.0","forks":84,"stargazersCount":789},{"name":"Android-Debug-Database","language":"Java","description":"A library for debugging android databases and shared preferences - Make Debugging Great Again","fullName":"amitshekhariitbhu\/Android-Debug-Database","updatedAt":"2020-11-20T15:15:17Z","gitUrl":"https:\/\/github.com\/amitshekhariitbhu\/Android-Debug-Database","license":"Apache License 2.0","forks":796,"stargazersCount":7593},{"name":"AndroidDatabaseLibraryComparison","language":"Java","description":null,"fullName":"Rightpoint\/AndroidDatabaseLibraryComparison","updatedAt":"2020-10-20T22:21:11Z","gitUrl":"https:\/\/github.com\/Rightpoint\/AndroidDatabaseLibraryComparison","license":"MIT License","forks":43,"stargazersCount":148},{"name":"LitePal","language":"Java","description":"An Android library that makes developers use SQLite database extremely easy.","fullName":"guolindev\/LitePal","updatedAt":"2020-11-20T07:35:43Z","gitUrl":"https:\/\/github.com\/guolindev\/LitePal","license":"Apache License 2.0","forks":1532,"stargazersCount":7389},{"name":"android_dbinspector","language":"Kotlin","description":"Android library for viewing and sharing in app databases.","fullName":"infinum\/android_dbinspector","updatedAt":"2020-11-18T14:27:05Z","gitUrl":"https:\/\/github.com\/infinum\/android_dbinspector","license":"Apache License 2.0","forks":90,"stargazersCount":870},{"name":"DBFlow","language":"Kotlin","description":"A blazing fast, powerful, and very simple ORM android database library that writes database code for you.","fullName":"agrosner\/DBFlow","updatedAt":"2020-11-18T05:36:17Z","gitUrl":"https:\/\/github.com\/agrosner\/DBFlow","license":"MIT License","forks":607,"stargazersCount":4786},{"name":"squidb","language":"Java","description":"SquiDB is a SQLite database library for Android and iOS","fullName":"yahoo\/squidb","updatedAt":"2020-11-16T10:56:00Z","gitUrl":"https:\/\/github.com\/yahoo\/squidb","license":"Apache License 2.0","forks":132,"stargazersCount":1322},{"name":"hyperlog-android","language":"Java","description":"Utility logger library for storing logs into database and push them to remote server for debugging","fullName":"hypertrack\/hyperlog-android","updatedAt":"2020-11-11T23:08:15Z","gitUrl":"https:\/\/github.com\/hypertrack\/hyperlog-android","license":null,"forks":96,"stargazersCount":644},{"name":"RoomDatabase","language":"Java","description":"Android Architecture Component - Room Persistency Library example","fullName":"ravi8x\/RoomDatabase","updatedAt":"2020-06-20T19:32:28Z","gitUrl":"https:\/\/github.com\/ravi8x\/RoomDatabase","license":null,"forks":16,"stargazersCount":35},{"name":"room-persistence-sample","language":"Java","description":"Implementation of Room Persistence Library","fullName":"ajaysaini-sgvu\/room-persistence-sample","updatedAt":"2020-11-18T21:15:07Z","gitUrl":"https:\/\/github.com\/ajaysaini-sgvu\/room-persistence-sample","license":null,"forks":44,"stargazersCount":88},{"name":"sprinkles","language":"Java","description":"Sprinkles is a boiler-plate-reduction-library for dealing with databases in android applications","fullName":"emilsjolander\/sprinkles","updatedAt":"2020-10-28T08:46:53Z","gitUrl":"https:\/\/github.com\/emilsjolander\/sprinkles","license":"Apache License 2.0","forks":84,"stargazersCount":789},{"name":"Android-Debug-Database","language":"Java","description":"A library for debugging android databases and shared preferences - Make Debugging Great Again","fullName":"amitshekhariitbhu\/Android-Debug-Database","updatedAt":"2020-11-20T15:15:17Z","gitUrl":"https:\/\/github.com\/amitshekhariitbhu\/Android-Debug-Database","license":"Apache License 2.0","forks":796,"stargazersCount":7593},{"name":"AndroidDatabaseLibraryComparison","language":"Java","description":null,"fullName":"Rightpoint\/AndroidDatabaseLibraryComparison","updatedAt":"2020-10-20T22:21:11Z","gitUrl":"https:\/\/github.com\/Rightpoint\/AndroidDatabaseLibraryComparison","license":"MIT License","forks":43,"stargazersCount":148},{"name":"LitePal","language":"Java","description":"An Android library that makes developers use SQLite database extremely easy.","fullName":"guolindev\/LitePal","updatedAt":"2020-11-20T07:35:43Z","gitUrl":"https:\/\/github.com\/guolindev\/LitePal","license":"Apache License 2.0","forks":1532,"stargazersCount":7389},{"name":"android_dbinspector","language":"Kotlin","description":"Android library for viewing and sharing in app databases.","fullName":"infinum\/android_dbinspector","updatedAt":"2020-11-18T14:27:05Z","gitUrl":"https:\/\/github.com\/infinum\/android_dbinspector","license":"Apache License 2.0","forks":90,"stargazersCount":870},{"name":"DBFlow","language":"Kotlin","description":"A blazing fast, powerful, and very simple ORM android database library that writes database code for you.","fullName":"agrosner\/DBFlow","updatedAt":"2020-11-18T05:36:17Z","gitUrl":"https:\/\/github.com\/agrosner\/DBFlow","license":"MIT License","forks":607,"stargazersCount":4786},{"name":"squidb","language":"Java","description":"SquiDB is a SQLite database library for Android and iOS","fullName":"yahoo\/squidb","updatedAt":"2020-11-16T10:56:00Z","gitUrl":"https:\/\/github.com\/yahoo\/squidb","license":"Apache License 2.0","forks":132,"stargazersCount":1322},{"name":"hyperlog-android","language":"Java","description":"Utility logger library for storing logs into database and push them to remote server for debugging","fullName":"hypertrack\/hyperlog-android","updatedAt":"2020-11-11T23:08:15Z","gitUrl":"https:\/\/github.com\/hypertrack\/hyperlog-android","license":null,"forks":96,"stargazersCount":644},{"name":"RoomDatabase","language":"Java","description":"Android Architecture Component - Room Persistency Library example","fullName":"ravi8x\/RoomDatabase","updatedAt":"2020-06-20T19:32:28Z","gitUrl":"https:\/\/github.com\/ravi8x\/RoomDatabase","license":null,"forks":16,"stargazersCount":35},{"name":"room-persistence-sample","language":"Java","description":"Implementation of Room Persistence Library","fullName":"ajaysaini-sgvu\/room-persistence-sample","updatedAt":"2020-11-18T21:15:07Z","gitUrl":"https:\/\/github.com\/ajaysaini-sgvu\/room-persistence-sample","license":null,"forks":44,"stargazersCount":88},{"name":"sprinkles","language":"Java","description":"Sprinkles is a boiler-plate-reduction-library for dealing with databases in android applications","fullName":"emilsjolander\/sprinkles","updatedAt":"2020-10-28T08:46:53Z","gitUrl":"https:\/\/github.com\/emilsjolander\/sprinkles","license":"Apache License 2.0","forks":84,"stargazersCount":789},{"name":"Android-Debug-Database","language":"Java","description":"A library for debugging android databases and shared preferences - Make Debugging Great Again","fullName":"amitshekhariitbhu\/Android-Debug-Database","updatedAt":"2020-11-20T15:15:17Z","gitUrl":"https:\/\/github.com\/amitshekhariitbhu\/Android-Debug-Database","license":"Apache License 2.0","forks":796,"stargazersCount":7593},{"name":"AndroidDatabaseLibraryComparison","language":"Java","description":null,"fullName":"Rightpoint\/AndroidDatabaseLibraryComparison","updatedAt":"2020-10-20T22:21:11Z","gitUrl":"https:\/\/github.com\/Rightpoint\/AndroidDatabaseLibraryComparison","license":"MIT License","forks":43,"stargazersCount":148},{"name":"LitePal","language":"Java","description":"An Android library that makes developers use SQLite database extremely easy.","fullName":"guolindev\/LitePal","updatedAt":"2020-11-20T07:35:43Z","gitUrl":"https:\/\/github.com\/guolindev\/LitePal","license":"Apache License 2.0","forks":1532,"stargazersCount":7389},{"name":"android_dbinspector","language":"Kotlin","description":"Android library for viewing and sharing in app databases.","fullName":"infinum\/android_dbinspector","updatedAt":"2020-11-18T14:27:05Z","gitUrl":"https:\/\/github.com\/infinum\/android_dbinspector","license":"Apache License 2.0","forks":90,"stargazersCount":870},{"name":"DBFlow","language":"Kotlin","description":"A blazing fast, powerful, and very simple ORM android database library that writes database code for you.","fullName":"agrosner\/DBFlow","updatedAt":"2020-11-18T05:36:17Z","gitUrl":"https:\/\/github.com\/agrosner\/DBFlow","license":"MIT License","forks":607,"stargazersCount":4786},{"name":"squidb","language":"Java","description":"SquiDB is a SQLite database library for Android and iOS","fullName":"yahoo\/squidb","updatedAt":"2020-11-16T10:56:00Z","gitUrl":"https:\/\/github.com\/yahoo\/squidb","license":"Apache License 2.0","forks":132,"stargazersCount":1322},{"name":"hyperlog-android","language":"Java","description":"Utility logger library for storing logs into database and push them to remote server for debugging","fullName":"hypertrack\/hyperlog-android","updatedAt":"2020-11-11T23:08:15Z","gitUrl":"https:\/\/github.com\/hypertrack\/hyperlog-android","license":null,"forks":96,"stargazersCount":644},{"name":"RoomDatabase","language":"Java","description":"Android Architecture Component - Room Persistency Library example","fullName":"ravi8x\/RoomDatabase","updatedAt":"2020-06-20T19:32:28Z","gitUrl":"https:\/\/github.com\/ravi8x\/RoomDatabase","license":null,"forks":16,"stargazersCount":35},{"name":"room-persistence-sample","language":"Java","description":"Implementation of Room Persistence Library","fullName":"ajaysaini-sgvu\/room-persistence-sample","updatedAt":"2020-11-18T21:15:07Z","gitUrl":"https:\/\/github.com\/ajaysaini-sgvu\/room-persistence-sample","license":null,"forks":44,"stargazersCount":88},{"name":"sprinkles","language":"Java","description":"Sprinkles is a boiler-plate-reduction-library for dealing with databases in android applications","fullName":"emilsjolander\/sprinkles","updatedAt":"2020-10-28T08:46:53Z","gitUrl":"https:\/\/github.com\/emilsjolander\/sprinkles","license":"Apache License 2.0","forks":84,"stargazersCount":789},{"name":"Android-Debug-Database","language":"Java","description":"A library for debugging android databases and shared preferences - Make Debugging Great Again","fullName":"amitshekhariitbhu\/Android-Debug-Database","updatedAt":"2020-11-20T15:15:17Z","gitUrl":"https:\/\/github.com\/amitshekhariitbhu\/Android-Debug-Database","license":"Apache License 2.0","forks":796,"stargazersCount":7593},{"name":"AndroidDatabaseLibraryComparison","language":"Java","description":null,"fullName":"Rightpoint\/AndroidDatabaseLibraryComparison","updatedAt":"2020-10-20T22:21:11Z","gitUrl":"https:\/\/github.com\/Rightpoint\/AndroidDatabaseLibraryComparison","license":"MIT License","forks":43,"stargazersCount":148},{"name":"LitePal","language":"Java","description":"An Android library that makes developers use SQLite database extremely easy.","fullName":"guolindev\/LitePal","updatedAt":"2020-11-20T07:35:43Z","gitUrl":"https:\/\/github.com\/guolindev\/LitePal","license":"Apache License 2.0","forks":1532,"stargazersCount":7389},{"name":"android_dbinspector","language":"Kotlin","description":"Android library for viewing and sharing in app databases.","fullName":"infinum\/android_dbinspector","updatedAt":"2020-11-18T14:27:05Z","gitUrl":"https:\/\/github.com\/infinum\/android_dbinspector","license":"Apache License 2.0","forks":90,"stargazersCount":870},{"name":"DBFlow","language":"Kotlin","description":"A blazing fast, powerful, and very simple ORM android database library that writes database code for you.","fullName":"agrosner\/DBFlow","updatedAt":"2020-11-18T05:36:17Z","gitUrl":"https:\/\/github.com\/agrosner\/DBFlow","license":"MIT License","forks":607,"stargazersCount":4786},{"name":"squidb","language":"Java","description":"SquiDB is a SQLite database library for Android and iOS","fullName":"yahoo\/squidb","updatedAt":"2020-11-16T10:56:00Z","gitUrl":"https:\/\/github.com\/yahoo\/squidb","license":"Apache License 2.0","forks":132,"stargazersCount":1322},{"name":"hyperlog-android","language":"Java","description":"Utility logger library for storing logs into database and push them to remote server for debugging","fullName":"hypertrack\/hyperlog-android","updatedAt":"2020-11-11T23:08:15Z","gitUrl":"https:\/\/github.com\/hypertrack\/hyperlog-android","license":null,"forks":96,"stargazersCount":644},{"name":"RoomDatabase","language":"Java","description":"Android Architecture Component - Room Persistency Library example","fullName":"ravi8x\/RoomDatabase","updatedAt":"2020-06-20T19:32:28Z","gitUrl":"https:\/\/github.com\/ravi8x\/RoomDatabase","license":null,"forks":16,"stargazersCount":35},{"name":"room-persistence-sample","language":"Java","description":"Implementation of Room Persistence Library","fullName":"ajaysaini-sgvu\/room-persistence-sample","updatedAt":"2020-11-18T21:15:07Z","gitUrl":"https:\/\/github.com\/ajaysaini-sgvu\/room-persistence-sample","license":null,"forks":44,"stargazersCount":88},{"name":"sprinkles","language":"Java","description":"Sprinkles is a boiler-plate-reduction-library for dealing with databases in android applications","fullName":"emilsjolander\/sprinkles","updatedAt":"2020-10-28T08:46:53Z","gitUrl":"https:\/\/github.com\/emilsjolander\/sprinkles","license":"Apache License 2.0","forks":84,"stargazersCount":789},{"name":"Android-Debug-Database","language":"Java","description":"A library for debugging android databases and shared preferences - Make Debugging Great Again","fullName":"amitshekhariitbhu\/Android-Debug-Database","updatedAt":"2020-11-20T15:15:17Z","gitUrl":"https:\/\/github.com\/amitshekhariitbhu\/Android-Debug-Database","license":"Apache License 2.0","forks":796,"stargazersCount":7593},{"name":"AndroidDatabaseLibraryComparison","language":"Java","description":null,"fullName":"Rightpoint\/AndroidDatabaseLibraryComparison","updatedAt":"2020-10-20T22:21:11Z","gitUrl":"https:\/\/github.com\/Rightpoint\/AndroidDatabaseLibraryComparison","license":"MIT License","forks":43,"stargazersCount":148},{"name":"LitePal","language":"Java","description":"An Android library that makes developers use SQLite database extremely easy.","fullName":"guolindev\/LitePal","updatedAt":"2020-11-20T07:35:43Z","gitUrl":"https:\/\/github.com\/guolindev\/LitePal","license":"Apache License 2.0","forks":1532,"stargazersCount":7389},{"name":"android_dbinspector","language":"Kotlin","description":"Android library for viewing and sharing in app databases.","fullName":"infinum\/android_dbinspector","updatedAt":"2020-11-18T14:27:05Z","gitUrl":"https:\/\/github.com\/infinum\/android_dbinspector","license":"Apache License 2.0","forks":90,"stargazersCount":870},{"name":"DBFlow","language":"Kotlin","description":"A blazing fast, powerful, and very simple ORM android database library that writes database code for you.","fullName":"agrosner\/DBFlow","updatedAt":"2020-11-18T05:36:17Z","gitUrl":"https:\/\/github.com\/agrosner\/DBFlow","license":"MIT License","forks":607,"stargazersCount":4786},{"name":"squidb","language":"Java","description":"SquiDB is a SQLite database library for Android and iOS","fullName":"yahoo\/squidb","updatedAt":"2020-11-16T10:56:00Z","gitUrl":"https:\/\/github.com\/yahoo\/squidb","license":"Apache License 2.0","forks":132,"stargazersCount":1322},{"name":"hyperlog-android","language":"Java","description":"Utility logger library for storing logs into database and push them to remote server for debugging","fullName":"hypertrack\/hyperlog-android","updatedAt":"2020-11-11T23:08:15Z","gitUrl":"https:\/\/github.com\/hypertrack\/hyperlog-android","license":null,"forks":96,"stargazersCount":644},{"name":"RoomDatabase","language":"Java","description":"Android Architecture Component - Room Persistency Library example","fullName":"ravi8x\/RoomDatabase","updatedAt":"2020-06-20T19:32:28Z","gitUrl":"https:\/\/github.com\/ravi8x\/RoomDatabase","license":null,"forks":16,"stargazersCount":35},{"name":"room-persistence-sample","language":"Java","description":"Implementation of Room Persistence Library","fullName":"ajaysaini-sgvu\/room-persistence-sample","updatedAt":"2020-11-18T21:15:07Z","gitUrl":"https:\/\/github.com\/ajaysaini-sgvu\/room-persistence-sample","license":null,"forks":44,"stargazersCount":88},{"name":"sprinkles","language":"Java","description":"Sprinkles is a boiler-plate-reduction-library for dealing with databases in android applications","fullName":"emilsjolander\/sprinkles","updatedAt":"2020-10-28T08:46:53Z","gitUrl":"https:\/\/github.com\/emilsjolander\/sprinkles","license":"Apache License 2.0","forks":84,"stargazersCount":789},{"name":"Android-Debug-Database","language":"Java","description":"A library for debugging android databases and shared preferences - Make Debugging Great Again","fullName":"amitshekhariitbhu\/Android-Debug-Database","updatedAt":"2020-11-20T15:15:17Z","gitUrl":"https:\/\/github.com\/amitshekhariitbhu\/Android-Debug-Database","license":"Apache License 2.0","forks":796,"stargazersCount":7593},{"name":"AndroidDatabaseLibraryComparison","language":"Java","description":null,"fullName":"Rightpoint\/AndroidDatabaseLibraryComparison","updatedAt":"2020-10-20T22:21:11Z","gitUrl":"https:\/\/github.com\/Rightpoint\/AndroidDatabaseLibraryComparison","license":"MIT License","forks":43,"stargazersCount":148},{"name":"LitePal","language":"Java","description":"An Android library that makes developers use SQLite database extremely easy.","fullName":"guolindev\/LitePal","updatedAt":"2020-11-20T07:35:43Z","gitUrl":"https:\/\/github.com\/guolindev\/LitePal","license":"Apache License 2.0","forks":1532,"stargazersCount":7389},{"name":"android_dbinspector","language":"Kotlin","description":"Android library for viewing and sharing in app databases.","fullName":"infinum\/android_dbinspector","updatedAt":"2020-11-18T14:27:05Z","gitUrl":"https:\/\/github.com\/infinum\/android_dbinspector","license":"Apache License 2.0","forks":90,"stargazersCount":870},{"name":"DBFlow","language":"Kotlin","description":"A blazing fast, powerful, and very simple ORM android database library that writes database code for you.","fullName":"agrosner\/DBFlow","updatedAt":"2020-11-18T05:36:17Z","gitUrl":"https:\/\/github.com\/agrosner\/DBFlow","license":"MIT License","forks":607,"stargazersCount":4786},{"name":"squidb","language":"Java","description":"SquiDB is a SQLite database library for Android and iOS","fullName":"yahoo\/squidb","updatedAt":"2020-11-16T10:56:00Z","gitUrl":"https:\/\/github.com\/yahoo\/squidb","license":"Apache License 2.0","forks":132,"stargazersCount":1322},{"name":"hyperlog-android","language":"Java","description":"Utility logger library for storing logs into database and push them to remote server for debugging","fullName":"hypertrack\/hyperlog-android","updatedAt":"2020-11-11T23:08:15Z","gitUrl":"https:\/\/github.com\/hypertrack\/hyperlog-android","license":null,"forks":96,"stargazersCount":644},{"name":"RoomDatabase","language":"Java","description":"Android Architecture Component - Room Persistency Library example","fullName":"ravi8x\/RoomDatabase","updatedAt":"2020-06-20T19:32:28Z","gitUrl":"https:\/\/github.com\/ravi8x\/RoomDatabase","license":null,"forks":16,"stargazersCount":35},{"name":"room-persistence-sample","language":"Java","description":"Implementation of Room Persistence Library","fullName":"ajaysaini-sgvu\/room-persistence-sample","updatedAt":"2020-11-18T21:15:07Z","gitUrl":"https:\/\/github.com\/ajaysaini-sgvu\/room-persistence-sample","license":null,"forks":44,"stargazersCount":88},{"name":"sprinkles","language":"Java","description":"Sprinkles is a boiler-plate-reduction-library for dealing with databases in android applications","fullName":"emilsjolander\/sprinkles","updatedAt":"2020-10-28T08:46:53Z","gitUrl":"https:\/\/github.com\/emilsjolander\/sprinkles","license":"Apache License 2.0","forks":84,"stargazersCount":789},{"name":"Android-Debug-Database","language":"Java","description":"A library for debugging android databases and shared preferences - Make Debugging Great Again","fullName":"amitshekhariitbhu\/Android-Debug-Database","updatedAt":"2020-11-20T15:15:17Z","gitUrl":"https:\/\/github.com\/amitshekhariitbhu\/Android-Debug-Database","license":"Apache License 2.0","forks":796,"stargazersCount":7593},{"name":"AndroidDatabaseLibraryComparison","language":"Java","description":null,"fullName":"Rightpoint\/AndroidDatabaseLibraryComparison","updatedAt":"2020-10-20T22:21:11Z","gitUrl":"https:\/\/github.com\/Rightpoint\/AndroidDatabaseLibraryComparison","license":"MIT License","forks":43,"stargazersCount":148},{"name":"LitePal","language":"Java","description":"An Android library that makes developers use SQLite database extremely easy.","fullName":"guolindev\/LitePal","updatedAt":"2020-11-20T07:35:43Z","gitUrl":"https:\/\/github.com\/guolindev\/LitePal","license":"Apache License 2.0","forks":1532,"stargazersCount":7389},{"name":"android_dbinspector","language":"Kotlin","description":"Android library for viewing and sharing in app databases.","fullName":"infinum\/android_dbinspector","updatedAt":"2020-11-18T14:27:05Z","gitUrl":"https:\/\/github.com\/infinum\/android_dbinspector","license":"Apache License 2.0","forks":90,"stargazersCount":870},{"name":"DBFlow","language":"Kotlin","description":"A blazing fast, powerful, and very simple ORM android database library that writes database code for you.","fullName":"agrosner\/DBFlow","updatedAt":"2020-11-18T05:36:17Z","gitUrl":"https:\/\/github.com\/agrosner\/DBFlow","license":"MIT License","forks":607,"stargazersCount":4786},{"name":"squidb","language":"Java","description":"SquiDB is a SQLite database library for Android and iOS","fullName":"yahoo\/squidb","updatedAt":"2020-11-16T10:56:00Z","gitUrl":"https:\/\/github.com\/yahoo\/squidb","license":"Apache License 2.0","forks":132,"stargazersCount":1322},{"name":"hyperlog-android","language":"Java","description":"Utility logger library for storing logs into database and push them to remote server for debugging","fullName":"hypertrack\/hyperlog-android","updatedAt":"2020-11-11T23:08:15Z","gitUrl":"https:\/\/github.com\/hypertrack\/hyperlog-android","license":null,"forks":96,"stargazersCount":644},{"name":"RoomDatabase","language":"Java","description":"Android Architecture Component - Room Persistency Library example","fullName":"ravi8x\/RoomDatabase","updatedAt":"2020-06-20T19:32:28Z","gitUrl":"https:\/\/github.com\/ravi8x\/RoomDatabase","license":null,"forks":16,"stargazersCount":35},{"name":"room-persistence-sample","language":"Java","description":"Implementation of Room Persistence Library","fullName":"ajaysaini-sgvu\/room-persistence-sample","updatedAt":"2020-11-18T21:15:07Z","gitUrl":"https:\/\/github.com\/ajaysaini-sgvu\/room-persistence-sample","license":null,"forks":44,"stargazersCount":88},{"name":"sprinkles","language":"Java","description":"Sprinkles is a boiler-plate-reduction-library for dealing with databases in android applications","fullName":"emilsjolander\/sprinkles","updatedAt":"2020-10-28T08:46:53Z","gitUrl":"https:\/\/github.com\/emilsjolander\/sprinkles","license":"Apache License 2.0","forks":84,"stargazersCount":789},{"name":"Android-Debug-Database","language":"Java","description":"A library for debugging android databases and shared preferences - Make Debugging Great Again","fullName":"amitshekhariitbhu\/Android-Debug-Database","updatedAt":"2020-11-20T15:15:17Z","gitUrl":"https:\/\/github.com\/amitshekhariitbhu\/Android-Debug-Database","license":"Apache License 2.0","forks":796,"stargazersCount":7593},{"name":"AndroidDatabaseLibraryComparison","language":"Java","description":null,"fullName":"Rightpoint\/AndroidDatabaseLibraryComparison","updatedAt":"2020-10-20T22:21:11Z","gitUrl":"https:\/\/github.com\/Rightpoint\/AndroidDatabaseLibraryComparison","license":"MIT License","forks":43,"stargazersCount":148},{"name":"LitePal","language":"Java","description":"An Android library that makes developers use SQLite database extremely easy.","fullName":"guolindev\/LitePal","updatedAt":"2020-11-20T07:35:43Z","gitUrl":"https:\/\/github.com\/guolindev\/LitePal","license":"Apache License 2.0","forks":1532,"stargazersCount":7389},{"name":"android_dbinspector","language":"Kotlin","description":"Android library for viewing and sharing in app databases.","fullName":"infinum\/android_dbinspector","updatedAt":"2020-11-18T14:27:05Z","gitUrl":"https:\/\/github.com\/infinum\/android_dbinspector","license":"Apache License 2.0","forks":90,"stargazersCount":870},{"name":"DBFlow","language":"Kotlin","description":"A blazing fast, powerful, and very simple ORM android database library that writes database code for you.","fullName":"agrosner\/DBFlow","updatedAt":"2020-11-18T05:36:17Z","gitUrl":"https:\/\/github.com\/agrosner\/DBFlow","license":"MIT License","forks":607,"stargazersCount":4786},{"name":"squidb","language":"Java","description":"SquiDB is a SQLite database library for Android and iOS","fullName":"yahoo\/squidb","updatedAt":"2020-11-16T10:56:00Z","gitUrl":"https:\/\/github.com\/yahoo\/squidb","license":"Apache License 2.0","forks":132,"stargazersCount":1322},{"name":"hyperlog-android","language":"Java","description":"Utility logger library for storing logs into database and push them to remote server for debugging","fullName":"hypertrack\/hyperlog-android","updatedAt":"2020-11-11T23:08:15Z","gitUrl":"https:\/\/github.com\/hypertrack\/hyperlog-android","license":null,"forks":96,"stargazersCount":644},{"name":"RoomDatabase","language":"Java","description":"Android Architecture Component - Room Persistency Library example","fullName":"ravi8x\/RoomDatabase","updatedAt":"2020-06-20T19:32:28Z","gitUrl":"https:\/\/github.com\/ravi8x\/RoomDatabase","license":null,"forks":16,"stargazersCount":35},{"name":"room-persistence-sample","language":"Java","description":"Implementation of Room Persistence Library","fullName":"ajaysaini-sgvu\/room-persistence-sample","updatedAt":"2020-11-18T21:15:07Z","gitUrl":"https:\/\/github.com\/ajaysaini-sgvu\/room-persistence-sample","license":null,"forks":44,"stargazersCount":88},{"name":"sprinkles","language":"Java","description":"Sprinkles is a boiler-plate-reduction-library for dealing with databases in android applications","fullName":"emilsjolander\/sprinkles","updatedAt":"2020-10-28T08:46:53Z","gitUrl":"https:\/\/github.com\/emilsjolander\/sprinkles","license":"Apache License 2.0","forks":84,"stargazersCount":789},{"name":"Android-Debug-Database","language":"Java","description":"A library for debugging android databases and shared preferences - Make Debugging Great Again","fullName":"amitshekhariitbhu\/Android-Debug-Database","updatedAt":"2020-11-20T15:15:17Z","gitUrl":"https:\/\/github.com\/amitshekhariitbhu\/Android-Debug-Database","license":"Apache License 2.0","forks":796,"stargazersCount":7593},{"name":"AndroidDatabaseLibraryComparison","language":"Java","description":null,"fullName":"Rightpoint\/AndroidDatabaseLibraryComparison","updatedAt":"2020-10-20T22:21:11Z","gitUrl":"https:\/\/github.com\/Rightpoint\/AndroidDatabaseLibraryComparison","license":"MIT License","forks":43,"stargazersCount":148},{"name":"LitePal","language":"Java","description":"An Android library that makes developers use SQLite database extremely easy.","fullName":"guolindev\/LitePal","updatedAt":"2020-11-20T07:35:43Z","gitUrl":"https:\/\/github.com\/guolindev\/LitePal","license":"Apache License 2.0","forks":1532,"stargazersCount":7389},{"name":"android_dbinspector","language":"Kotlin","description":"Android library for viewing and sharing in app databases.","fullName":"infinum\/android_dbinspector","updatedAt":"2020-11-18T14:27:05Z","gitUrl":"https:\/\/github.com\/infinum\/android_dbinspector","license":"Apache License 2.0","forks":90,"stargazersCount":870},{"name":"DBFlow","language":"Kotlin","description":"A blazing fast, powerful, and very simple ORM android database library that writes database code for you.","fullName":"agrosner\/DBFlow","updatedAt":"2020-11-18T05:36:17Z","gitUrl":"https:\/\/github.com\/agrosner\/DBFlow","license":"MIT License","forks":607,"stargazersCount":4786},{"name":"squidb","language":"Java","description":"SquiDB is a SQLite database library for Android and iOS","fullName":"yahoo\/squidb","updatedAt":"2020-11-16T10:56:00Z","gitUrl":"https:\/\/github.com\/yahoo\/squidb","license":"Apache License 2.0","forks":132,"stargazersCount":1322},{"name":"hyperlog-android","language":"Java","description":"Utility logger library for storing logs into database and push them to remote server for debugging","fullName":"hypertrack\/hyperlog-android","updatedAt":"2020-11-11T23:08:15Z","gitUrl":"https:\/\/github.com\/hypertrack\/hyperlog-android","license":null,"forks":96,"stargazersCount":644},{"name":"RoomDatabase","language":"Java","description":"Android Architecture Component - Room Persistency Library example","fullName":"ravi8x\/RoomDatabase","updatedAt":"2020-06-20T19:32:28Z","gitUrl":"https:\/\/github.com\/ravi8x\/RoomDatabase","license":null,"forks":16,"stargazersCount":35},{"name":"room-persistence-sample","language":"Java","description":"Implementation of Room Persistence Library","fullName":"ajaysaini-sgvu\/room-persistence-sample","updatedAt":"2020-11-18T21:15:07Z","gitUrl":"https:\/\/github.com\/ajaysaini-sgvu\/room-persistence-sample","license":null,"forks":44,"stargazersCount":88},{"name":"sprinkles","language":"Java","description":"Sprinkles is a boiler-plate-reduction-library for dealing with databases in android applications","fullName":"emilsjolander\/sprinkles","updatedAt":"2020-10-28T08:46:53Z","gitUrl":"https:\/\/github.com\/emilsjolander\/sprinkles","license":"Apache License 2.0","forks":84,"stargazersCount":789}]}